lazy_slides
