Metadata-Version: 1.0
Name: lazy-slides
Version: 0.3
Summary: Build a presentation by downloading images based on keywords.
Home-page: http://code.google.com/p/lazy-slides/
Author: Austin Bingham
Author-email: austin.bingham@gmail.com
License: MIT
Download-URL: http://code.google.com/p/lazy-slides/source/checkout
Keywords: presentation
Platform: any
Classifier: Development Status :: 4 - Beta
Classifier: Environment :: Console
Classifier: Intended Audience :: End Users/Desktop
Classifier: License :: OSI Approved :: MIT License
Classifier: Operating System :: OS Independent
Classifier: Programming Language :: Python
Classifier: Topic :: Multimedia :: Graphics :: Presentation
